ta_numba/__init__.py
ta_numba/helpers.py
ta_numba/momentum.py
ta_numba/others.py
ta_numba/strategy.py
ta_numba/streaming_strategy.py
ta_numba/trend.py
ta_numba/volatility.py
ta_numba/volume.py
ta_numba/warmup.py
ta_numba/streaming/__init__.py
ta_numba/streaming/base.py
ta_numba/streaming/momentum.py
ta_numba/streaming/others.py
ta_numba/streaming/trend.py
ta_numba/streaming/volatility.py
ta_numba/streaming/volume.py
ta_numba-0.2.3.dist-info/licenses/LICENSE
ta_numba-0.2.3.dist-info/METADATA
ta_numba-0.2.3.dist-info/WHEEL
ta_numba-0.2.3.dist-info/top_level.txt
ta_numba-0.2.3.dist-info/RECORD
