Metadata-Version: 2.4
Name: ta-numba
Version: 0.2.3
Summary: A high-performance technical analysis library with JIT compilation and streaming capabilities for real-time trading.
Author-email: Beomgyu Joeng <jaden.b.jeong@gmail.com>
License: MIT
Project-URL: Homepage, https://github.com/JadenJ09/ta-numba
Project-URL: Issues, https://github.com/JadenJ09/ta-numba/issues
Project-URL: Repository, https://github.com/JadenJ09/ta-numba
Project-URL: Documentation, https://github.com/JadenJ09/ta-numba#readme
Keywords: technical-analysis,quantitative-analysis,financial-engineering,trading,indicators,numba,performance,streaming,real-time,jit-compilation
Classifier: Programming Language :: Python :: 3
Classifier: Operating System :: OS Independent
Classifier: Intended Audience :: Financial and Insurance Industry
Classifier: Topic :: Office/Business :: Financial :: Investment
Classifier: Development Status :: 4 - Beta
Classifier: Topic :: Scientific/Engineering :: Mathematics
Classifier: Topic :: Software Development :: Libraries :: Python Modules
Requires-Python: >=3.11
License-File: LICENSE
Requires-Dist: numpy
Requires-Dist: numba
Provides-Extra: dev
Requires-Dist: pytest; extra == "dev"
Requires-Dist: pandas; extra == "dev"
Requires-Dist: ta; extra == "dev"
Dynamic: license-file
